rfernet-0.3.5.dist-info/METADATA
rfernet-0.3.5.dist-info/WHEEL
rfernet.libs/libcrypto-3dc39733.so.1.1
rfernet.libs/libssl-b6e07dfa.so.1.1
rfernet/__init__.py
rfernet/__init__.pyi
rfernet/py.typed
rfernet/rfernet.cpython-39-aarch64-linux-gnu.so
rfernet-0.3.5.dist-info/RECORD
