Metadata-Version: 2.4
Name: rfernet
Version: 0.3.5
Summary: Fast Fernet bindings for Python
Keywords: fast,fernet
Author: Aviram Hassan <aviramyhassan@gmail.com>
Author-email: Aviram Hassan <aviramyhassan@gmail.com>
License: MIT
